src/fpga/spi_device.v
/*
Simple SPI Device Implementation

This module reads an 8-bit value when the select wire is pulled
low, after which it's then outputted to the register data_out
*/

module spi_device (
	input wire clk, // PIN_V10
	input wire rst,
	input wire cs, // PIN_V7
	input wire mosi, // PIN_V8
	output wire miso, // PIN_V9
	output reg [7:0] data_out
	);
	
	reg [7:0] shift;
	reg [3:0] bit_count; // count starts at 1, so need to count to 8 instead of 7
	wire cs_n = ~cs;
	
	// bit shifts on falling clock edge to capture stabalized 
	// MOSI value after changes on the rising clock edge
	always @(negedge clk) begin
		if (cs_n) begin
			shift <= {mosi, shift[7:1]};
			bit_count <= bit_count + 1;
		end
		else begin
			shift <= 8'd0;
			bit_count <= 4'd0;
		end
	end
	
	always @(posedge clk) begin
		// output data when select wire pulled up and counter = 8
		if (bit_count == 4'd8 && cs)
			data_out <= shift;
	end
	
	assign miso = (cs_n) ? clk : 1'bz; // arbitrary assignment
	
endmodule

src/fpga/spi_device_tb.v
`timescale 1ns / 1ps

module spi_device_tb;

reg clk, rst, cs, mosi;
wire miso;
wire [7:0] data_out;
integer i;

spi_device dut(clk, rst, cs, mosi, miso, data_out);

initial begin
	$dumpfile("spi_device.vcd");
	$dumpvars(0, spi_device_tb);

	clk = 0;
	rst = 1;
	cs = 1;
	mosi = 0;
	
	#10 @(posedge clk);
	rst = 0;
	cs = 0;
	
	// send decimal number 189 (1011 1101)
	for (i = 7; i >= 0; i = i - 1) begin
		mosi = (8'd189 >> i);
		@(posedge clk);
	end
	
	cs = 1;
	#20 $finish;
end

always #5 clk = ~clk;

endmodule

src/fpga/simulation/spi_device.vcd
$date
	Sat Nov 23 13:42:23 2024
$end
$version
	Icarus Verilog
$end
$timescale
	1ps
$end
$scope module spi_device_tb $end
$var wire 1 ! miso $end
$var wire 8 " data_out [7:0] $end
$var reg 1 # clk $end
$var reg 1 $ cs $end
$var reg 1 % mosi $end
$var reg 1 & rst $end
$var integer 32 ' i [31:0] $end
$scope module dut $end
$var wire 1 # clk $end
$var wire 1 $ cs $end
$var wire 1 ( cs_n $end
$var wire 1 % mosi $end
$var wire 1 & rst $end
$var wire 1 ! miso $end
$var reg 4 ) bit_count [3:0] $end
$var reg 8 * data_out [7:0] $end
$var reg 8 + shift [7:0] $end
$upscope $end
$upscope $end
$enddefinitions $end
$comment Show the parameter values. $end
$dumpall
$end
#0
$dumpvars
b0 +
bx *
b0 )
0(
bx '
1&
0%
1$
0#
bx "
z!
$end
#5000
1#
#10000
0#
#15000
1!
1(
1%
b111 '
0$
0&
1#
#20000
b1 )
b10000000 +
0!
0#
#25000
0%
b110 '
1!
1#
#30000
b10 )
b1000000 +
0!
0#
#35000
1%
b101 '
1!
1#
#40000
b11 )
b10100000 +
0!
0#
#45000
b100 '
1!
1#
#50000
b100 )
b11010000 +
0!
0#
#55000
b11 '
1!
1#
#60000
b101 )
b11101000 +
0!
0#
#65000
b10 '
1!
1#
#70000
b110 )
b11110100 +
0!
0#
#75000
0%
b1 '
1!
1#
#80000
b111 )
b1111010 +
0!
0#
#85000
1%
b0 '
1!
1#
#90000
b1000 )
b10111101 +
0!
0#
#95000
b10111101 "
b10111101 *
0(
1$
b11111111111111111111111111111111 '
z!
1#
#100000
b0 )
b0 +
0#
